{
  "version": 1,
  "image": "10-the-wrestlers.jpg",
  "width": 1262,
  "height": 1600,
  "aspect": 0.7887,
  "tonal": {
    "mean": 0.2904178615955366,
    "std": 0.197409533502311,
    "p05": 0.1843137254901961,
    "p95": 0.9058823529411765,
    "edge_density": 0.034330951827757125
  },
  "palette": [
    "#37332b",
    "#484236",
    "#f6e2bf",
    "#6e614e",
    "#948366"
  ],
  "lines": [
    {
      "x1": 0.01858736059479554,
      "y1": 0.603515625,
      "x2": 0.01858736059479554,
      "y2": 0.01953125,
      "angle_deg": -90.0,
      "length": 0.4586686718846632,
      "class": "vertical"
    },
    {
      "x1": 0.9591078066914498,
      "y1": 0.9443359375,
      "x2": 0.9591078066914498,
      "y2": 0.4404296875,
      "angle_deg": -90.0,
      "length": 0.3957743055058298,
      "class": "vertical"
    },
    {
      "x1": 0.28004956629491945,
      "y1": 0.03515625,
      "x2": 0.8748451053283767,
      "y2": 0.03515625,
      "angle_deg": 0.0,
      "length": 0.36816214465658587,
      "class": "horizontal"
    },
    {
      "x1": 0.03717472118959108,
      "y1": 0.94140625,
      "x2": 0.03717472118959108,
      "y2": 0.5068359375,
      "angle_deg": -90.0,
      "length": 0.3413169882753765,
      "class": "vertical"
    },
    {
      "x1": 0.01734820322180917,
      "y1": 0.98046875,
      "x2": 0.01734820322180917,
      "y2": 0.578125,
      "angle_deg": -90.0,
      "length": 0.3160058408302362,
      "class": "vertical"
    },
    {
      "x1": 0.436183395291202,
      "y1": 0.9833984375,
      "x2": 0.8488228004956629,
      "y2": 0.9833984375,
      "angle_deg": 0.0,
      "length": 0.25541248785550646,
      "class": "horizontal"
    },
    {
      "x1": 0.9603469640644362,
      "y1": 0.47265625,
      "x2": 0.9603469640644362,
      "y2": 0.181640625,
      "angle_deg": -90.0,
      "length": 0.22856733147429706,
      "class": "vertical"
    },
    {
      "x1": 0.9789343246592317,
      "y1": 0.9833984375,
      "x2": 0.9789343246592317,
      "y2": 0.7021484375,
      "angle_deg": -90.0,
      "length": 0.22089728679395151,
      "class": "vertical"
    },
    {
      "x1": 0.6034696406443618,
      "y1": 0.0205078125,
      "x2": 0.9318463444857497,
      "y2": 0.0205078125,
      "angle_deg": 0.0,
      "length": 0.20325618402915677,
      "class": "horizontal"
    },
    {
      "x1": 0.28376703841387857,
      "y1": 0.01953125,
      "x2": 0.6071871127633209,
      "y2": 0.01953125,
      "angle_deg": 0.0,
      "length": 0.20018816615701857,
      "class": "horizontal"
    },
    {
      "x1": 0.9801734820322181,
      "y1": 0.6298828125,
      "x2": 0.9801734820322181,
      "y2": 0.3798828125,
      "angle_deg": -90.0,
      "length": 0.1963531438168458,
      "class": "vertical"
    },
    {
      "x1": 0.9814126394052045,
      "y1": 0.3896484375,
      "x2": 0.9814126394052045,
      "y2": 0.14453125,
      "angle_deg": -90.0,
      "length": 0.19251812147667302,
      "class": "vertical"
    }
  ],
  "horizon": {
    "y": 0.1640625,
    "angle_deg": 0.0,
    "confidence": 1.0,
    "method": "gradient"
  },
  "vanishing_point": null,
  "saliency": {
    "peak": [
      0.990086741016109,
      0.0
    ],
    "regions": [
      {
        "cx": 0.9665718864147707,
        "cy": 0.9703229884796807,
        "x": 0.9231722428748451,
        "y": 0.931640625,
        "w": 0.0768277571251549,
        "h": 0.068359375,
        "area_frac": 0.0041688448729863695
      },
      {
        "cx": 0.9643788327447151,
        "cy": 0.026356730554729327,
        "x": 0.919454770755886,
        "y": 0.0,
        "w": 0.080545229244114,
        "h": 0.0615234375,
        "area_frac": 0.004068405359355638
      },
      {
        "cx": 0.02873958553711931,
        "cy": 0.970241044207317,
        "x": 0.0,
        "y": 0.9326171875,
        "w": 0.06815365551425032,
        "h": 0.0673828125,
        "area_frac": 0.003721102462825279
      }
    ]
  },
  "faces": [],
  "symmetry": {
    "vertical": 0.9339636272843304,
    "vertical_axis_x": 0.5,
    "horizontal": 0.8919004312124414,
    "horizontal_axis_y": 0.5
  },
  "subject_anchor": {
    "x": 0.990086741016109,
    "y": 0.0,
    "source": "saliency"
  },
  "grids": {
    "thirds": 0.0,
    "phi": 0.0,
    "best": "thirds"
  },
  "suggested_primitives": [
    {
      "type": "horizon_line",
      "y": 0.164,
      "angle": 0.0,
      "label": "horizon",
      "confidence": 1.0,
      "why": "luminance split / dominant horizontal (gradient)"
    },
    {
      "type": "symmetry_axis",
      "orientation": "vertical",
      "pos": 0.5,
      "confidence": 0.93,
      "why": "strong left/right mirror correlation"
    },
    {
      "type": "subject_anchor",
      "x": 0.99,
      "y": 0.0,
      "r": 0.035,
      "label": "saliency",
      "confidence": 0.6,
      "why": "strongest subject signal: saliency"
    }
  ]
}