{
  "version": 1,
  "image": "10-baby-tenement-hallway.jpg",
  "width": 1536,
  "height": 1226,
  "aspect": 1.2529,
  "tonal": {
    "mean": 0.5649854473039215,
    "std": 0.26915480851438195,
    "p05": 0.07450980392156863,
    "p95": 0.8666666666666667,
    "edge_density": 0.0356343711750306
  },
  "palette": [
    "#d2d2d2",
    "#b6b6b6",
    "#1c1c1c",
    "#8f8f8f",
    "#565656"
  ],
  "lines": [
    {
      "x1": 0.0,
      "y1": 0.0024479804161566705,
      "x2": 0.8642578125,
      "y2": 0.0024479804161566705,
      "angle_deg": 0.0,
      "length": 0.6755794083677688,
      "class": "horizontal"
    },
    {
      "x1": 0.99609375,
      "y1": 0.98531211750306,
      "x2": 0.99609375,
      "y2": 0.4700122399020808,
      "angle_deg": -90.0,
      "length": 0.3213773230766448,
      "class": "vertical"
    },
    {
      "x1": 0.736328125,
      "y1": 0.2582619339045288,
      "x2": 0.7412109375,
      "y2": 0.576499388004896,
      "angle_deg": 88.89829388479363,
      "length": 0.19851200333614158,
      "class": "vertical"
    },
    {
      "x1": 0.6494140625,
      "y1": 0.3463892288861689,
      "x2": 0.6533203125,
      "y2": 0.6352509179926561,
      "angle_deg": 89.02897806892084,
      "length": 0.1801803838725531,
      "class": "vertical"
    },
    {
      "x1": 0.859375,
      "y1": 0.4418604651162791,
      "x2": 0.8701171875,
      "y2": 0.7209302325581395,
      "angle_deg": 87.23787168662119,
      "length": 0.1742500186455347,
      "class": "vertical"
    },
    {
      "x1": 0.6474609375,
      "y1": 0.4259485924112607,
      "x2": 0.650390625,
      "y2": 0.7050183598531212,
      "angle_deg": 89.24615166692924,
      "length": 0.17406264218631948,
      "class": "vertical"
    },
    {
      "x1": 0.89453125,
      "y1": 0.6083231334149327,
      "x2": 0.8974609375,
      "y2": 0.8665850673194615,
      "angle_deg": 89.18542295024028,
      "length": 0.16108662432674017,
      "class": "vertical"
    },
    {
      "x1": 0.9697265625,
      "y1": 0.4614443084455324,
      "x2": 0.9794921875,
      "y2": 0.7099143206854345,
      "angle_deg": 87.17982752755152,
      "length": 0.1551513197083334,
      "class": "vertical"
    },
    {
      "x1": 0.3544921875,
      "y1": 0.627906976744186,
      "x2": 0.357421875,
      "y2": 0.8727050183598531,
      "angle_deg": 89.14062775635531,
      "length": 0.15269048740712768,
      "class": "vertical"
    },
    {
      "x1": 0.4580078125,
      "y1": 0.10648714810281518,
      "x2": 0.474609375,
      "y2": 0.34761321909424725,
      "angle_deg": 85.06791257173515,
      "length": 0.1509421056971468,
      "class": "vertical"
    },
    {
      "x1": 0.828125,
      "y1": 0.784577723378213,
      "x2": 0.828125,
      "y2": 0.5458996328029376,
      "angle_deg": -90.0,
      "length": 0.14885647980984734,
      "class": "vertical"
    },
    {
      "x1": 0.4228515625,
      "y1": 0.2607099143206854,
      "x2": 0.4228515625,
      "y2": 0.023255813953488372,
      "angle_deg": -90.0,
      "length": 0.14809311324671992,
      "class": "vertical"
    }
  ],
  "horizon": {
    "y": 0.8861689106487148,
    "angle_deg": 0.0,
    "confidence": 0.8856816207749597,
    "method": "gradient"
  },
  "vanishing_point": null,
  "saliency": {
    "peak": [
      0.5380859375,
      0.5973072215422277
    ],
    "regions": [
      {
        "cx": 0.45480176968829794,
        "cy": 0.25669474758453026,
        "x": 0.3837890625,
        "y": 0.11015911872705018,
        "w": 0.1611328125,
        "h": 0.26805385556915545,
        "area_frac": 0.027619864978580173
      },
      {
        "cx": 0.9204573272524241,
        "cy": 0.29080366638805083,
        "x": 0.8349609375,
        "y": 0.12607099143206854,
        "w": 0.1650390625,
        "h": 0.3084455324357405,
        "area_frac": 0.0266265682374541
      },
      {
        "cx": 0.5339872880291596,
        "cy": 0.583135738950884,
        "x": 0.486328125,
        "y": 0.423500611995104,
        "w": 0.1064453125,
        "h": 0.24357405140758873,
        "area_frac": 0.013383806992044063
      }
    ]
  },
  "faces": [],
  "symmetry": {
    "vertical": 0.7476413280984829,
    "vertical_axis_x": 0.625,
    "horizontal": 0.8679765047683019,
    "horizontal_axis_y": 0.4
  },
  "subject_anchor": {
    "x": 0.5380859375,
    "y": 0.5973072215422277,
    "source": "saliency"
  },
  "grids": {
    "thirds": 0.15028418236641047,
    "phi": 0.3191952208569483,
    "best": "phi"
  },
  "suggested_primitives": [
    {
      "type": "horizon_line",
      "y": 0.886,
      "angle": 0.0,
      "label": "horizon",
      "confidence": 0.89,
      "why": "luminance split / dominant horizontal (gradient)"
    },
    {
      "type": "subject_anchor",
      "x": 0.538,
      "y": 0.597,
      "r": 0.035,
      "label": "saliency",
      "confidence": 0.6,
      "why": "strongest subject signal: saliency"
    }
  ]
}