{
  "version": 1,
  "image": "06-enfants-place-hebert.jpg",
  "width": 791,
  "height": 908,
  "aspect": 0.8711,
  "tonal": {
    "mean": 0.47598286829448555,
    "std": 0.3272567506885505,
    "p05": 0.043137254901960784,
    "p95": 0.9647058823529412,
    "edge_density": 0.08000941205299711
  },
  "palette": [
    "#171717",
    "#e9e9e9",
    "#494949",
    "#bababa",
    "#858585"
  ],
  "lines": [
    {
      "x1": 0.2579013906447535,
      "y1": 0.8744493392070485,
      "x2": 0.28824273072060685,
      "y2": 0.5099118942731278,
      "angle_deg": -85.85288068942505,
      "length": 0.27558838297079047,
      "class": "vertical"
    },
    {
      "x1": 0.0,
      "y1": 0.0011013215859030838,
      "x2": 0.3906447534766119,
      "y2": 0.048458149779735685,
      "angle_deg": 7.922321653000664,
      "length": 0.25907031128328006,
      "class": "horizontal"
    },
    {
      "x1": 0.020227560050568902,
      "y1": 0.9548458149779736,
      "x2": 0.2920353982300885,
      "y2": 0.7180616740088106,
      "angle_deg": -45.0,
      "length": 0.2524920701034166,
      "class": "diagonal"
    },
    {
      "x1": 0.8988621997471555,
      "y1": 0.7786343612334802,
      "x2": 0.911504424778761,
      "y2": 0.4834801762114537,
      "angle_deg": -87.86308914624276,
      "length": 0.2227056327100991,
      "class": "vertical"
    },
    {
      "x1": 0.05309734513274336,
      "y1": 0.1817180616740088,
      "x2": 0.37168141592920356,
      "y2": 0.197136563876652,
      "angle_deg": 3.1798301198642345,
      "length": 0.20958683598589095,
      "class": "horizontal"
    },
    {
      "x1": 0.011378002528445006,
      "y1": 0.02973568281938326,
      "x2": 0.22882427307206069,
      "y2": 0.21916299559471367,
      "angle_deg": 45.0,
      "length": 0.2019936560827333,
      "class": "diagonal"
    },
    {
      "x1": 0.010113780025284451,
      "y1": 0.8513215859030837,
      "x2": 0.225031605562579,
      "y2": 0.6640969162995595,
      "angle_deg": -45.0,
      "length": 0.19964489263991084,
      "class": "diagonal"
    },
    {
      "x1": 0.26422250316055623,
      "y1": 0.5055066079295154,
      "x2": 0.40581542351453853,
      "y2": 0.28193832599118945,
      "angle_deg": -61.1134182330893,
      "length": 0.1925287712264939,
      "class": "diagonal"
    },
    {
      "x1": 0.16308470290771176,
      "y1": 0.00881057268722467,
      "x2": 0.28697850821744625,
      "y2": 0.22136563876651982,
      "angle_deg": 63.079814241693924,
      "length": 0.17974755318172198,
      "class": "diagonal"
    },
    {
      "x1": 0.3463969658659924,
      "y1": 0.711453744493392,
      "x2": 0.5398230088495575,
      "y2": 0.5429515418502202,
      "angle_deg": -45.0,
      "length": 0.17968040337591976,
      "class": "diagonal"
    },
    {
      "x1": 0.9292035398230089,
      "y1": 0.6563876651982379,
      "x2": 0.9393173198482933,
      "y2": 0.4185022026431718,
      "angle_deg": -87.87890360333854,
      "length": 0.1794922502738811,
      "class": "vertical"
    },
    {
      "x1": 0.42098609355246525,
      "y1": 0.551762114537445,
      "x2": 0.5562579013906448,
      "y2": 0.7477973568281938,
      "angle_deg": 58.98893069625842,
      "length": 0.17246426342726248,
      "class": "diagonal"
    }
  ],
  "horizon": {
    "y": 0.1894273127753304,
    "angle_deg": 3.1798301198642345,
    "confidence": 1.0,
    "method": "both"
  },
  "vanishing_point": {
    "x": 0.479503673577399,
    "y": 0.530887585389439,
    "inliers": 9,
    "confidence": 1.0
  },
  "saliency": {
    "peak": [
      0.42604298356510745,
      0.8513215859030837
    ],
    "regions": [
      {
        "cx": 0.48550345797985867,
        "cy": 0.5914852972308189,
        "x": 0.42098609355246525,
        "y": 0.5242290748898678,
        "w": 0.12389380530973451,
        "h": 0.1299559471365639,
        "area_frac": 0.012777279638220732
      },
      {
        "cx": 0.4235166450561641,
        "cy": 0.8491799233676669,
        "x": 0.36283185840707965,
        "y": 0.7918502202643172,
        "w": 0.1213653603034134,
        "h": 0.1145374449339207,
        "area_frac": 0.010862845781562401
      },
      {
        "cx": 0.3750431740116845,
        "cy": 0.33454718909336656,
        "x": 0.31605562579013907,
        "y": 0.28193832599118945,
        "w": 0.12262958280657396,
        "h": 0.10572687224669604,
        "area_frac": 0.01006504898166042
      }
    ]
  },
  "faces": [],
  "symmetry": {
    "vertical": 0.6802611009414121,
    "vertical_axis_x": 0.5125,
    "horizontal": 0.7437876651565051,
    "horizontal_axis_y": 0.625
  },
  "subject_anchor": {
    "x": 0.42604298356510745,
    "y": 0.8513215859030837,
    "source": "saliency"
  },
  "grids": {
    "thirds": 0.01607184504141193,
    "phi": 0.09704292188772318,
    "best": "phi"
  },
  "suggested_primitives": [
    {
      "type": "horizon_line",
      "y": 0.189,
      "angle": 3.2,
      "label": "horizon",
      "confidence": 1.0,
      "why": "luminance split / dominant horizontal (both)"
    },
    {
      "type": "vanishing_point",
      "x": 0.48,
      "y": 0.531,
      "confidence": 1.0,
      "why": "9 converging diagonals"
    },
    {
      "type": "subject_anchor",
      "x": 0.426,
      "y": 0.851,
      "r": 0.035,
      "label": "saliency",
      "confidence": 0.6,
      "why": "strongest subject signal: saliency"
    },
    {
      "type": "leading_line",
      "points": [
        [
          0.02,
          0.955
        ],
        [
          0.292,
          0.718
        ]
      ],
      "arrow": true,
      "label": "leading line",
      "confidence": 0.5,
      "why": "strong diagonal converging on VP"
    }
  ]
}