{
  "version": 1,
  "image": "05-woman-high-plains.jpg",
  "width": 1231,
  "height": 1600,
  "aspect": 0.7694,
  "tonal": {
    "mean": 0.7283601711014774,
    "std": 0.1794677109356337,
    "p05": 0.37254901960784315,
    "p95": 0.9058823529411765,
    "edge_density": 0.013756253970775095
  },
  "palette": [
    "#dcdcdc",
    "#bababa",
    "#8f8f8f",
    "#6b6b6b",
    "#3b3b3b"
  ],
  "lines": [
    {
      "x1": 0.7852604828462516,
      "y1": 0.9580078125,
      "x2": 0.9987293519695044,
      "y2": 0.943359375,
      "angle_deg": -5.10216525235819,
      "length": 0.1305998384541273,
      "class": "horizontal"
    },
    {
      "x1": 0.5984752223634053,
      "y1": 0.529296875,
      "x2": 0.6759847522236341,
      "y2": 0.42578125,
      "angle_deg": -60.080791311442496,
      "length": 0.09469594534074272,
      "class": "diagonal"
    },
    {
      "x1": 0.6264294790343075,
      "y1": 0.451171875,
      "x2": 0.7306226175349428,
      "y2": 0.37109375,
      "angle_deg": -45.0,
      "length": 0.08979207077213605,
      "class": "diagonal"
    },
    {
      "x1": 0.7318932655654383,
      "y1": 0.693359375,
      "x2": 0.7687420584498094,
      "y2": 0.587890625,
      "angle_deg": -74.96956947656672,
      "length": 0.08658665953568986,
      "class": "diagonal"
    },
    {
      "x1": 0.46886912325285895,
      "y1": 0.45703125,
      "x2": 0.554002541296061,
      "y2": 0.3701171875,
      "angle_deg": -53.02723751043195,
      "length": 0.08625713474862647,
      "class": "diagonal"
    },
    {
      "x1": 0.8653113087674714,
      "y1": 0.998046875,
      "x2": 0.9987293519695044,
      "y2": 0.9921875,
      "angle_deg": -3.2704879231835653,
      "length": 0.08143410605542693,
      "class": "horizontal"
    },
    {
      "x1": 0.20076238881829733,
      "y1": 0.4111328125,
      "x2": 0.32655654383735705,
      "y2": 0.4423828125,
      "angle_deg": 17.912509385963265,
      "length": 0.08056067373730585,
      "class": "diagonal"
    },
    {
      "x1": 0.3062261753494282,
      "y1": 0.34765625,
      "x2": 0.4104193138500635,
      "y2": 0.28515625,
      "angle_deg": -37.971603761050396,
      "length": 0.08054206635196993,
      "class": "diagonal"
    },
    {
      "x1": 0.5209656925031766,
      "y1": 0.2626953125,
      "x2": 0.5476493011435832,
      "y2": 0.1640625,
      "angle_deg": -78.25436657471205,
      "length": 0.07987681957278979,
      "class": "diagonal"
    },
    {
      "x1": 0.5806861499364676,
      "y1": 0.16015625,
      "x2": 0.625158831003812,
      "y2": 0.25,
      "angle_deg": 69.17144420979318,
      "length": 0.07621643221470141,
      "class": "diagonal"
    },
    {
      "x1": 0.6454891994917408,
      "y1": 0.435546875,
      "x2": 0.7623888182973316,
      "y2": 0.4560546875,
      "angle_deg": 12.85809017299818,
      "length": 0.07306781137969796,
      "class": "diagonal"
    },
    {
      "x1": 0.6721728081321474,
      "y1": 0.197265625,
      "x2": 0.6975857687420585,
      "y2": 0.2822265625,
      "angle_deg": 77.05349048436307,
      "length": 0.06912116518758366,
      "class": "diagonal"
    }
  ],
  "horizon": {
    "y": 0.7646484375,
    "angle_deg": 0.0,
    "confidence": 1.0,
    "method": "gradient"
  },
  "vanishing_point": {
    "x": 0.6836401282534001,
    "y": 0.36763460631985584,
    "inliers": 4,
    "confidence": 0.8
  },
  "saliency": {
    "peak": [
      0.5196950444726811,
      0.2265625
    ],
    "regions": [
      {
        "cx": 0.5183968329861975,
        "cy": 0.2348460823399914,
        "x": 0.43456162642947904,
        "y": 0.1650390625,
        "w": 0.16772554002541296,
        "h": 0.140625,
        "area_frac": 0.0173324332909784
      },
      {
        "cx": 0.7505892253070174,
        "cy": 0.41712378233367886,
        "x": 0.6886912325285895,
        "y": 0.3583984375,
        "w": 0.12706480304955528,
        "h": 0.1064453125,
        "area_frac": 0.006584041454891995
      },
      {
        "cx": 0.4662242888924546,
        "cy": 0.4601786226135879,
        "x": 0.4027954256670902,
        "y": 0.4248046875,
        "w": 0.12960609911054638,
        "h": 0.0732421875,
        "area_frac": 0.005817185514612452
      }
    ]
  },
  "faces": [],
  "symmetry": {
    "vertical": 0.7002554482215826,
    "vertical_axis_x": 0.5,
    "horizontal": 0.6008830643775386,
    "horizontal_axis_y": 0.425
  },
  "subject_anchor": {
    "x": 0.5196950444726811,
    "y": 0.2265625,
    "source": "saliency"
  },
  "grids": {
    "thirds": 0.33700199345140314,
    "phi": 0.2167961292087951,
    "best": "thirds"
  },
  "suggested_primitives": [
    {
      "type": "horizon_line",
      "y": 0.765,
      "angle": 0.0,
      "label": "horizon",
      "confidence": 1.0,
      "why": "luminance split / dominant horizontal (gradient)"
    },
    {
      "type": "vanishing_point",
      "x": 0.684,
      "y": 0.368,
      "confidence": 0.8,
      "why": "4 converging diagonals"
    },
    {
      "type": "subject_anchor",
      "x": 0.52,
      "y": 0.227,
      "r": 0.035,
      "label": "saliency",
      "confidence": 0.6,
      "why": "strongest subject signal: saliency"
    },
    {
      "type": "leading_line",
      "points": [
        [
          0.598,
          0.529
        ],
        [
          0.676,
          0.426
        ]
      ],
      "arrow": true,
      "label": "leading line",
      "confidence": 0.19,
      "why": "strong diagonal converging on VP"
    }
  ]
}