{
  "version": 1,
  "image": "03-monolith-face-of-half-dome.jpg",
  "width": 843,
  "height": 1137,
  "aspect": 0.7414,
  "tonal": {
    "mean": 0.39273913709505537,
    "std": 0.25566095648184467,
    "p05": 0.1607843137254902,
    "p95": 0.9176470588235294,
    "edge_density": 0.11571429306653491
  },
  "palette": [
    "#312d2e",
    "#4e4e4f",
    "#717271",
    "#e5e4df",
    "#9fa09d"
  ],
  "lines": [
    {
      "x1": 0.02766798418972332,
      "y1": 0.7890625,
      "x2": 0.6798418972332015,
      "y2": 0.3056640625,
      "angle_deg": -45.0,
      "length": 0.5492111602228671,
      "class": "diagonal"
    },
    {
      "x1": 0.014492753623188406,
      "y1": 0.7802734375,
      "x2": 0.014492753623188406,
      "y2": 0.177734375,
      "angle_deg": -90.0,
      "length": 0.48406571176767693,
      "class": "vertical"
    },
    {
      "x1": 0.026350461133069828,
      "y1": 0.7841796875,
      "x2": 0.5625823451910409,
      "y2": 0.373046875,
      "angle_deg": -45.968676914933745,
      "length": 0.45940589825510514,
      "class": "diagonal"
    },
    {
      "x1": 0.16469038208168643,
      "y1": 0.6962890625,
      "x2": 0.6851119894598156,
      "y2": 0.310546875,
      "angle_deg": -45.0,
      "length": 0.4382594106828939,
      "class": "diagonal"
    },
    {
      "x1": 0.015810276679841896,
      "y1": 0.7275390625,
      "x2": 0.4453227931488801,
      "y2": 0.4091796875,
      "angle_deg": -45.0,
      "length": 0.3617027035003125,
      "class": "diagonal"
    },
    {
      "x1": 0.2318840579710145,
      "y1": 0.7822265625,
      "x2": 0.5006587615283268,
      "y2": 0.3916015625,
      "angle_deg": -62.97841840882297,
      "length": 0.3522748625015253,
      "class": "diagonal"
    },
    {
      "x1": 0.08168642951251646,
      "y1": 0.7607421875,
      "x2": 0.43741765480895917,
      "y2": 0.4228515625,
      "angle_deg": -52.033416459694934,
      "length": 0.3443224476036628,
      "class": "diagonal"
    },
    {
      "x1": 0.9828722002635046,
      "y1": 0.685546875,
      "x2": 0.9828722002635046,
      "y2": 0.2587890625,
      "angle_deg": -90.0,
      "length": 0.3428471896960694,
      "class": "vertical"
    },
    {
      "x1": 0.25823451910408435,
      "y1": 0.8056640625,
      "x2": 0.3847167325428195,
      "y2": 0.4033203125,
      "angle_deg": -76.88356387460853,
      "length": 0.3318922738119665,
      "class": "diagonal"
    },
    {
      "x1": 0.21212121212121213,
      "y1": 0.765625,
      "x2": 0.5994729907773386,
      "y2": 0.478515625,
      "angle_deg": -45.0,
      "length": 0.32619814364752103,
      "class": "diagonal"
    },
    {
      "x1": 0.015810276679841896,
      "y1": 0.6806640625,
      "x2": 0.4479578392621871,
      "y2": 0.46484375,
      "angle_deg": -33.971320846562314,
      "length": 0.31029318610078815,
      "class": "diagonal"
    },
    {
      "x1": 0.015810276679841896,
      "y1": 0.9814453125,
      "x2": 0.015810276679841896,
      "y2": 0.5986328125,
      "angle_deg": -90.0,
      "length": 0.30754255917816753,
      "class": "vertical"
    }
  ],
  "horizon": {
    "y": 0.7138671875,
    "angle_deg": 0.0,
    "confidence": 0.9827882566306818,
    "method": "gradient"
  },
  "vanishing_point": {
    "x": 0.44630420397665416,
    "y": 0.4702656054637733,
    "inliers": 8,
    "confidence": 1.0
  },
  "saliency": {
    "peak": [
      0.9894598155467721,
      0.6796875
    ],
    "regions": [
      {
        "cx": 0.9014479002196478,
        "cy": 0.8092463991942875,
        "x": 0.764163372859025,
        "y": 0.6123046875,
        "w": 0.23583662714097497,
        "h": 0.3876953125,
        "area_frac": 0.05966423748353096
      },
      {
        "cx": 0.0714937303550618,
        "cy": 0.9025001014903291,
        "x": 0.0,
        "y": 0.8095703125,
        "w": 0.152832674571805,
        "h": 0.1904296875,
        "area_frac": 0.022284667325428196
      },
      {
        "cx": 0.08426852204232392,
        "cy": 0.6891931245005993,
        "x": 0.0,
        "y": 0.6357421875,
        "w": 0.17523056653491437,
        "h": 0.111328125,
        "area_frac": 0.016102344779314888
      }
    ]
  },
  "faces": [],
  "symmetry": {
    "vertical": 0.8331992553014728,
    "vertical_axis_x": 0.5,
    "horizontal": 0.6627122784828982,
    "horizontal_axis_y": 0.375
  },
  "subject_anchor": {
    "x": 0.9894598155467721,
    "y": 0.6796875,
    "source": "saliency"
  },
  "grids": {
    "thirds": 0.23731010710496336,
    "phi": 0.18275956568041016,
    "best": "thirds"
  },
  "suggested_primitives": [
    {
      "type": "vanishing_point",
      "x": 0.446,
      "y": 0.47,
      "confidence": 1.0,
      "why": "8 converging diagonals"
    },
    {
      "type": "leading_line",
      "points": [
        [
          0.028,
          0.789
        ],
        [
          0.68,
          0.306
        ]
      ],
      "arrow": true,
      "label": "leading line",
      "confidence": 1.0,
      "why": "strong diagonal converging on VP"
    },
    {
      "type": "horizon_line",
      "y": 0.714,
      "angle": 0.0,
      "label": "horizon",
      "confidence": 0.98,
      "why": "luminance split / dominant horizontal (gradient)"
    },
    {
      "type": "leading_line",
      "points": [
        [
          0.026,
          0.784
        ],
        [
          0.563,
          0.373
        ]
      ],
      "arrow": true,
      "label": "leading line",
      "confidence": 0.92,
      "why": "strong diagonal converging on VP"
    }
  ]
}