{
  "version": 1,
  "image": "01-vanishing-race-navaho.jpg",
  "width": 1599,
  "height": 1295,
  "aspect": 1.2347,
  "tonal": {
    "mean": 0.2650238870804655,
    "std": 0.24057252437473456,
    "p05": 0.13333333333333333,
    "p95": 0.996078431372549,
    "edge_density": 0.02623053943003619
  },
  "palette": [
    "#2d251e",
    "#453427",
    "#6a4d33",
    "#fdfdfb",
    "#c0a07d"
  ],
  "lines": [
    {
      "x1": 0.0205078125,
      "y1": 0.9493365500603136,
      "x2": 0.833984375,
      "y2": 0.9493365500603136,
      "angle_deg": 0.0,
      "length": 0.6322561067104626,
      "class": "horizontal"
    },
    {
      "x1": 0.0458984375,
      "y1": 0.9215922798552473,
      "x2": 0.0458984375,
      "y2": 0.026537997587454766,
      "angle_deg": -90.0,
      "length": 0.5631861118597399,
      "class": "vertical"
    },
    {
      "x1": 0.033203125,
      "y1": 0.8974668275030157,
      "x2": 0.033203125,
      "y2": 0.29191797346200243,
      "angle_deg": -90.0,
      "length": 0.38102348807761377,
      "class": "vertical"
    },
    {
      "x1": 0.6484375,
      "y1": 0.045838359469240045,
      "x2": 0.9775390625,
      "y2": 0.045838359469240045,
      "angle_deg": 0.0,
      "length": 0.2557866842274021,
      "class": "horizontal"
    },
    {
      "x1": 0.6513671875,
      "y1": 0.9589867310012062,
      "x2": 0.9765625,
      "y2": 0.9517490952955368,
      "angle_deg": -1.032244691565731,
      "length": 0.25279166478631576,
      "class": "horizontal"
    },
    {
      "x1": 0.0322265625,
      "y1": 0.9324487334137516,
      "x2": 0.0322265625,
      "y2": 0.5645355850422196,
      "angle_deg": -90.0,
      "length": 0.23149833438978523,
      "class": "vertical"
    },
    {
      "x1": 0.1044921875,
      "y1": 0.9469240048250904,
      "x2": 0.390625,
      "y2": 0.9469240048250904,
      "angle_deg": 0.0,
      "length": 0.22239020320067893,
      "class": "horizontal"
    },
    {
      "x1": 0.0732421875,
      "y1": 0.04221954161640531,
      "x2": 0.3525390625,
      "y2": 0.04221954161640531,
      "angle_deg": 0.0,
      "length": 0.21707712667370027,
      "class": "horizontal"
    },
    {
      "x1": 0.015625,
      "y1": 0.05307599517490953,
      "x2": 0.287109375,
      "y2": 0.05307599517490953,
      "angle_deg": 0.0,
      "length": 0.21100503921429606,
      "class": "horizontal"
    },
    {
      "x1": 0.955078125,
      "y1": 0.6924004825090471,
      "x2": 0.955078125,
      "y2": 0.3703256936067551,
      "angle_deg": -90.0,
      "length": 0.20265591895761528,
      "class": "vertical"
    },
    {
      "x1": 0.0341796875,
      "y1": 0.42581423401688784,
      "x2": 0.0341796875,
      "y2": 0.10494571773220748,
      "angle_deg": -90.0,
      "length": 0.20189690802518975,
      "class": "vertical"
    },
    {
      "x1": 0.0361328125,
      "y1": 0.971049457177322,
      "x2": 0.0361328125,
      "y2": 0.661037394451146,
      "angle_deg": -90.0,
      "length": 0.19506580963336004,
      "class": "vertical"
    }
  ],
  "horizon": {
    "y": 0.158021712907117,
    "angle_deg": 0.0,
    "confidence": 0.5950620420300272,
    "method": "gradient"
  },
  "vanishing_point": null,
  "saliency": {
    "peak": [
      0.9921875,
      0.0
    ],
    "regions": [
      {
        "cx": 0.6348047018401248,
        "cy": 0.023782700881588667,
        "x": 0.564453125,
        "y": 0.0,
        "w": 0.1416015625,
        "h": 0.05910735826296743,
        "area_frac": 0.00641774728588661
      },
      {
        "cx": 0.9689634015175219,
        "cy": 0.034817647511741906,
        "x": 0.9287109375,
        "y": 0.0,
        "w": 0.0712890625,
        "h": 0.08202653799758745,
        "area_frac": 0.004706112409529554
      },
      {
        "cx": 0.49201172908946533,
        "cy": 0.02226048719620481,
        "x": 0.44140625,
        "y": 0.0,
        "w": 0.103515625,
        "h": 0.054282267792521106,
        "area_frac": 0.004450486278648975
      }
    ]
  },
  "faces": [],
  "symmetry": {
    "vertical": 0.9913557035193958,
    "vertical_axis_x": 0.5,
    "horizontal": 0.9881492629744455,
    "horizontal_axis_y": 0.5
  },
  "subject_anchor": {
    "x": 0.9921875,
    "y": 0.0,
    "source": "saliency"
  },
  "grids": {
    "thirds": 0.0,
    "phi": 0.0,
    "best": "thirds"
  },
  "suggested_primitives": [
    {
      "type": "symmetry_axis",
      "orientation": "vertical",
      "pos": 0.5,
      "confidence": 0.99,
      "why": "strong left/right mirror correlation"
    },
    {
      "type": "horizon_line",
      "y": 0.158,
      "angle": 0.0,
      "label": "horizon",
      "confidence": 0.6,
      "why": "luminance split / dominant horizontal (gradient)"
    },
    {
      "type": "subject_anchor",
      "x": 0.992,
      "y": 0.0,
      "r": 0.035,
      "label": "saliency",
      "confidence": 0.6,
      "why": "strongest subject signal: saliency"
    }
  ]
}