{
  "version": 1,
  "image": "03-cotton-pickers-at-six-thirty.jpg",
  "width": 1600,
  "height": 1124,
  "aspect": 1.4235,
  "tonal": {
    "mean": 0.5055570185306391,
    "std": 0.22251706910648045,
    "p05": 0.11764705882352941,
    "p95": 0.803921568627451,
    "edge_density": 0.03107750565020862
  },
  "palette": [
    "#a8a8a8",
    "#8a8a8a",
    "#242424",
    "#5c5c5c",
    "#c9c9c9"
  ],
  "lines": [
    {
      "x1": 0.306640625,
      "y1": 0.048678720445062586,
      "x2": 0.9736328125,
      "y2": 0.048678720445062586,
      "angle_deg": 0.0,
      "length": 0.5458697594623682,
      "class": "horizontal"
    },
    {
      "x1": 0.9775390625,
      "y1": 0.6828929068150209,
      "x2": 0.9775390625,
      "y2": 0.06954102920723226,
      "angle_deg": -90.0,
      "length": 0.35245763385491125,
      "class": "vertical"
    },
    {
      "x1": 0.02734375,
      "y1": 0.717663421418637,
      "x2": 0.02734375,
      "y2": 0.3713490959666203,
      "angle_deg": -90.0,
      "length": 0.1990066912242016,
      "class": "vertical"
    },
    {
      "x1": 0.65625,
      "y1": 0.952712100139082,
      "x2": 0.896484375,
      "y2": 0.952712100139082,
      "angle_deg": 0.0,
      "length": 0.19660902024559673,
      "class": "horizontal"
    },
    {
      "x1": 0.369140625,
      "y1": 0.3184979137691238,
      "x2": 0.3720703125,
      "y2": 0.06397774687065369,
      "angle_deg": -89.06080905426442,
      "length": 0.14627758141546685,
      "class": "vertical"
    },
    {
      "x1": 0.345703125,
      "y1": 0.9554937413073713,
      "x2": 0.517578125,
      "y2": 0.9554937413073713,
      "angle_deg": 0.0,
      "length": 0.14066336407815053,
      "class": "horizontal"
    },
    {
      "x1": 0.5693359375,
      "y1": 0.29346314325452016,
      "x2": 0.5751953125,
      "y2": 0.05006954102920723,
      "angle_deg": -88.03634246594804,
      "length": 0.13994632213647054,
      "class": "vertical"
    },
    {
      "x1": 0.6259765625,
      "y1": 0.26008344923504867,
      "x2": 0.634765625,
      "y2": 0.03616133518776078,
      "angle_deg": -86.80046029043743,
      "length": 0.12887589931359217,
      "class": "vertical"
    },
    {
      "x1": 0.52734375,
      "y1": 0.24339360222531292,
      "x2": 0.5322265625,
      "y2": 0.04172461752433936,
      "angle_deg": -88.02506598911803,
      "length": 0.11595630875492322,
      "class": "vertical"
    },
    {
      "x1": 0.978515625,
      "y1": 0.8595271210013908,
      "x2": 0.978515625,
      "y2": 0.6689847009735744,
      "angle_deg": -90.0,
      "length": 0.10949364135628761,
      "class": "vertical"
    },
    {
      "x1": 0.5986328125,
      "y1": 0.5173852573018081,
      "x2": 0.630859375,
      "y2": 0.33657858136300417,
      "angle_deg": -75.75653942645218,
      "length": 0.10719433707174181,
      "class": "diagonal"
    },
    {
      "x1": 0.77734375,
      "y1": 0.5869262865090403,
      "x2": 0.78125,
      "y2": 0.7663421418636995,
      "angle_deg": 88.22395574664127,
      "length": 0.10314940442991857,
      "class": "vertical"
    }
  ],
  "horizon": {
    "y": 0.866481223922114,
    "angle_deg": 0.0,
    "confidence": 0.7233724959816,
    "method": "gradient"
  },
  "vanishing_point": null,
  "saliency": {
    "peak": [
      0.2578125,
      0.14603616133518776
    ],
    "regions": [
      {
        "cx": 0.5863195329446854,
        "cy": 0.4424025173550876,
        "x": 0.384765625,
        "y": 0.2267037552155772,
        "w": 0.3662109375,
        "h": 0.5493741307371349,
        "area_frac": 0.0782676134388039
      },
      {
        "cx": 0.2651539224232356,
        "cy": 0.22372996153750646,
        "x": 0.208984375,
        "y": 0.0,
        "w": 0.12890625,
        "h": 0.4422809457579972,
        "area_frac": 0.03720037595618915
      },
      {
        "cx": 0.0707434863791189,
        "cy": 0.0939594009946692,
        "x": 0.0,
        "y": 0.0,
        "w": 0.1357421875,
        "h": 0.24061196105702365,
        "area_frac": 0.022629357180111265
      }
    ]
  },
  "faces": [],
  "symmetry": {
    "vertical": 0.7494288283792687,
    "vertical_axis_x": 0.5,
    "horizontal": 0.7642474013231404,
    "horizontal_axis_y": 0.5
  },
  "subject_anchor": {
    "x": 0.2578125,
    "y": 0.14603616133518776,
    "source": "saliency"
  },
  "grids": {
    "thirds": 0.0958781013998572,
    "phi": 0.0,
    "best": "thirds"
  },
  "suggested_primitives": [
    {
      "type": "horizon_line",
      "y": 0.866,
      "angle": 0.0,
      "label": "horizon",
      "confidence": 0.72,
      "why": "luminance split / dominant horizontal (gradient)"
    },
    {
      "type": "subject_anchor",
      "x": 0.258,
      "y": 0.146,
      "r": 0.035,
      "label": "saliency",
      "confidence": 0.6,
      "why": "strongest subject signal: saliency"
    }
  ]
}