{
  "version": 1,
  "image": "02-council-of-war.jpg",
  "width": 1600,
  "height": 1303,
  "aspect": 1.2279,
  "tonal": {
    "mean": 0.4458757445993103,
    "std": 0.1778513569473742,
    "p05": 0.16862745098039217,
    "p95": 0.7176470588235294,
    "edge_density": 0.0506640156062425
  },
  "palette": [
    "#896c55",
    "#a48a6f",
    "#6a4c3b",
    "#c3ac8f",
    "#2e2d30"
  ],
  "lines": [
    {
      "x1": 0.1416015625,
      "y1": 0.9603841536614646,
      "x2": 0.654296875,
      "y2": 0.9603841536614646,
      "angle_deg": 0.0,
      "length": 0.3977198543533523,
      "class": "horizontal"
    },
    {
      "x1": 0.1689453125,
      "y1": 0.04561824729891957,
      "x2": 0.521484375,
      "y2": 0.04561824729891957,
      "angle_deg": 0.0,
      "length": 0.27347974746963843,
      "class": "horizontal"
    },
    {
      "x1": 0.5263671875,
      "y1": 0.8739495798319328,
      "x2": 0.8056640625,
      "y2": 0.9279711884753902,
      "angle_deg": 8.94176159031166,
      "length": 0.21932815592722854,
      "class": "diagonal"
    },
    {
      "x1": 0.9609375,
      "y1": 0.7779111644657863,
      "x2": 0.9609375,
      "y2": 0.4417767106842737,
      "angle_deg": -90.0,
      "length": 0.2121172556551212,
      "class": "vertical"
    },
    {
      "x1": 0.634765625,
      "y1": 0.5378151260504201,
      "x2": 0.798828125,
      "y2": 0.33613445378151263,
      "angle_deg": -45.0,
      "length": 0.1799874598565001,
      "class": "diagonal"
    },
    {
      "x1": 0.76171875,
      "y1": 0.23169267707082833,
      "x2": 0.806640625,
      "y2": 0.46938775510204084,
      "angle_deg": 76.92087621993318,
      "length": 0.1539919876684217,
      "class": "diagonal"
    },
    {
      "x1": 0.5458984375,
      "y1": 0.38415366146458585,
      "x2": 0.560546875,
      "y2": 0.14165666266506602,
      "angle_deg": -85.75315739297653,
      "length": 0.1534487780234141,
      "class": "vertical"
    },
    {
      "x1": 0.33203125,
      "y1": 0.2797118847539016,
      "x2": 0.486328125,
      "y2": 0.40336134453781514,
      "angle_deg": 33.10027886348053,
      "length": 0.14288222826659647,
      "class": "diagonal"
    },
    {
      "x1": 0.654296875,
      "y1": 0.3877551020408163,
      "x2": 0.8251953125,
      "y2": 0.4249699879951981,
      "angle_deg": 10.045330369496698,
      "length": 0.1346372659132946,
      "class": "diagonal"
    },
    {
      "x1": 0.6640625,
      "y1": 0.39135654261704683,
      "x2": 0.6875,
      "y2": 0.5978391356542617,
      "angle_deg": 82.05652818940959,
      "length": 0.13156296027227002,
      "class": "vertical"
    },
    {
      "x1": 0.310546875,
      "y1": 0.31932773109243695,
      "x2": 0.46875,
      "y2": 0.25690276110444177,
      "angle_deg": -17.79598892393038,
      "length": 0.1288923821531403,
      "class": "diagonal"
    },
    {
      "x1": 0.0380859375,
      "y1": 0.6566626650660264,
      "x2": 0.0380859375,
      "y2": 0.453781512605042,
      "angle_deg": -90.0,
      "length": 0.12802791502041244,
      "class": "vertical"
    }
  ],
  "horizon": {
    "y": 0.14285714285714285,
    "angle_deg": 0.0,
    "confidence": 1.0,
    "method": "gradient"
  },
  "vanishing_point": {
    "x": 0.6423985272988506,
    "y": 0.3005766759358149,
    "inliers": 3,
    "confidence": 0.6
  },
  "saliency": {
    "peak": [
      0.1318359375,
      0.7779111644657863
    ],
    "regions": [
      {
        "cx": 0.506619750170035,
        "cy": 0.6334987628941977,
        "x": 0.4248046875,
        "y": 0.43217286914765907,
        "w": 0.21875,
        "h": 0.3457382953181273,
        "area_frac": 0.030164409513805522
      },
      {
        "cx": 0.12351777529906632,
        "cy": 0.7167023782864634,
        "x": 0.0576171875,
        "y": 0.595438175270108,
        "w": 0.1240234375,
        "h": 0.2545018007202881,
        "area_frac": 0.024108080732292918
      },
      {
        "cx": 0.8263039083819151,
        "cy": 0.40242460665734914,
        "x": 0.73046875,
        "y": 0.32292917166866747,
        "w": 0.1796875,
        "h": 0.18847539015606243,
        "area_frac": 0.02362859206182473
      }
    ]
  },
  "faces": [],
  "symmetry": {
    "vertical": 0.8522550190953915,
    "vertical_axis_x": 0.5,
    "horizontal": 0.8745475306170334,
    "horizontal_axis_y": 0.5
  },
  "subject_anchor": {
    "x": 0.1318359375,
    "y": 0.7779111644657863,
    "source": "saliency"
  },
  "grids": {
    "thirds": 0.20340169741639666,
    "phi": 0.15878673606483085,
    "best": "thirds"
  },
  "suggested_primitives": [
    {
      "type": "horizon_line",
      "y": 0.143,
      "angle": 0.0,
      "label": "horizon",
      "confidence": 1.0,
      "why": "luminance split / dominant horizontal (gradient)"
    },
    {
      "type": "symmetry_axis",
      "orientation": "vertical",
      "pos": 0.5,
      "confidence": 0.85,
      "why": "strong left/right mirror correlation"
    },
    {
      "type": "subject_anchor",
      "x": 0.132,
      "y": 0.778,
      "r": 0.035,
      "label": "saliency",
      "confidence": 0.6,
      "why": "strongest subject signal: saliency"
    },
    {
      "type": "vanishing_point",
      "x": 0.642,
      "y": 0.301,
      "confidence": 0.6,
      "why": "3 converging diagonals"
    }
  ]
}