{"version":1,"image":"07-the-street-design-for-a-poster.jpg","grid":{"type":"phi"},"primitives":[{"type":"frame_in_frame","x":0.159,"y":0.147,"w":0.657,"h":0.600,"label":"REPRODUCED PHOTOGRAPH"},{"type":"subject_anchor","x":0.477,"y":0.647,"r":0.035,"label":"CARRIAGE"},{"type":"polyline","points":[[0.555,0.268],[0.639,0.384],[0.669,0.548]],"label":"RIGHT TREE TRUNK"},{"type":"horizon_line","y":0.16,"angle":0,"label":"UPPER PRINT EDGE"}],"notes":"A horse and carriage cross the pale street inside a small mounted reproduction, bracketed by the dark tree and building masses."}
