{
  "version": 1,
  "image": "01-exterior-sekundra-bagh.jpg",
  "width": 1600,
  "height": 1280,
  "aspect": 1.25,
  "tonal": {
    "mean": 0.6513230131796308,
    "std": 0.1381145766133162,
    "p05": 0.3568627450980392,
    "p95": 0.7843137254901961,
    "edge_density": 0.021921979929792428
  },
  "palette": [
    "#d1c498",
    "#b8a77c",
    "#a18e69",
    "#846f50",
    "#664d34"
  ],
  "lines": [
    {
      "x1": 0.546875,
      "y1": 0.5103785103785103,
      "x2": 0.7001953125,
      "y2": 0.5006105006105006,
      "angle_deg": -2.917007286627713,
      "length": 0.11988979841188029,
      "class": "horizontal"
    },
    {
      "x1": 0.1162109375,
      "y1": 0.6275946275946276,
      "x2": 0.26953125,
      "y2": 0.6178266178266179,
      "angle_deg": -2.917007286627713,
      "length": 0.11988979841188029,
      "class": "horizontal"
    },
    {
      "x1": 0.40234375,
      "y1": 0.3076923076923077,
      "x2": 0.5224609375,
      "y2": 0.3626373626373626,
      "angle_deg": 20.095231191904816,
      "length": 0.09988544257596665,
      "class": "diagonal"
    },
    {
      "x1": 0.177734375,
      "y1": 0.6288156288156288,
      "x2": 0.3037109375,
      "y2": 0.6092796092796092,
      "angle_deg": -7.0703448201575965,
      "length": 0.09913438059561415,
      "class": "horizontal"
    },
    {
      "x1": 0.294921875,
      "y1": 0.5848595848595849,
      "x2": 0.4091796875,
      "y2": 0.575091575091575,
      "angle_deg": -3.9115718125286625,
      "length": 0.08943720463685832,
      "class": "horizontal"
    },
    {
      "x1": 0.40625,
      "y1": 0.4945054945054945,
      "x2": 0.5166015625,
      "y2": 0.49206349206349204,
      "angle_deg": -1.0139787227853019,
      "length": 0.08619180019718217,
      "class": "horizontal"
    },
    {
      "x1": 0.703125,
      "y1": 0.49206349206349204,
      "x2": 0.8125,
      "y2": 0.4884004884004884,
      "angle_deg": -1.5343414997007687,
      "length": 0.08544629963782485,
      "class": "horizontal"
    },
    {
      "x1": 0.4130859375,
      "y1": 0.38583638583638585,
      "x2": 0.494140625,
      "y2": 0.3064713064713065,
      "angle_deg": -38.06565109873044,
      "length": 0.0803997487532756,
      "class": "diagonal"
    },
    {
      "x1": 0.6162109375,
      "y1": 0.6971916971916972,
      "x2": 0.6162109375,
      "y2": 0.575091575091575,
      "angle_deg": -90.0,
      "length": 0.07626398513596942,
      "class": "vertical"
    },
    {
      "x1": 0.3134765625,
      "y1": 0.5641025641025641,
      "x2": 0.4091796875,
      "y2": 0.5445665445665445,
      "angle_deg": -9.2726017772003,
      "length": 0.07572825557753125,
      "class": "diagonal"
    },
    {
      "x1": 0.16015625,
      "y1": 0.6385836385836385,
      "x2": 0.16015625,
      "y2": 0.5201465201465202,
      "angle_deg": -90.0,
      "length": 0.07397606558189034,
      "class": "vertical"
    },
    {
      "x1": 0.6162109375,
      "y1": 0.5921855921855922,
      "x2": 0.703125,
      "y2": 0.6031746031746031,
      "angle_deg": 5.774325902663275,
      "length": 0.06822110803953021,
      "class": "horizontal"
    }
  ],
  "horizon": {
    "y": 0.4932844932844933,
    "angle_deg": -1.0139787227853019,
    "confidence": 1.0,
    "method": "both"
  },
  "vanishing_point": null,
  "saliency": {
    "peak": [
      0.3203125,
      0.518925518925519
    ],
    "regions": [
      {
        "cx": 0.498703641975149,
        "cy": 0.4856918403930488,
        "x": 0.123046875,
        "y": 0.2857142857142857,
        "w": 0.7919921875,
        "h": 0.3516483516483517,
        "area_frac": 0.11525106837606838
      }
    ]
  },
  "faces": [],
  "symmetry": {
    "vertical": 0.830337863783911,
    "vertical_axis_x": 0.5625,
    "horizontal": 0.6914419510346905,
    "horizontal_axis_y": 0.55
  },
  "subject_anchor": {
    "x": 0.3203125,
    "y": 0.518925518925519,
    "source": "saliency"
  },
  "grids": {
    "thirds": 0.21171118066317537,
    "phi": 0.29725194054047416,
    "best": "phi"
  },
  "suggested_primitives": [
    {
      "type": "horizon_line",
      "y": 0.493,
      "angle": -1.0,
      "label": "horizon",
      "confidence": 1.0,
      "why": "luminance split / dominant horizontal (both)"
    },
    {
      "type": "symmetry_axis",
      "orientation": "vertical",
      "pos": 0.562,
      "confidence": 0.83,
      "why": "strong left/right mirror correlation"
    },
    {
      "type": "subject_anchor",
      "x": 0.32,
      "y": 0.519,
      "r": 0.035,
      "label": "saliency",
      "confidence": 0.6,
      "why": "strongest subject signal: saliency"
    }
  ]
}