{
  "version": 1,
  "image": "12-golden-temple-amritsar.jpg",
  "width": 1296,
  "height": 1600,
  "aspect": 0.81,
  "tonal": {
    "mean": 0.5504103830728612,
    "std": 0.28290717061802734,
    "p05": 0.10980392156862745,
    "p95": 1.0,
    "edge_density": 0.1508288412243667
  },
  "palette": [
    "#cfbda7",
    "#9c8974",
    "#695645",
    "#2f231f",
    "#fefefe"
  ],
  "lines": [
    {
      "x1": 0.026537997587454766,
      "y1": 0.9267578125,
      "x2": 0.026537997587454766,
      "y2": 0.0205078125,
      "angle_deg": -90.0,
      "length": 0.7043621452908876,
      "class": "vertical"
    },
    {
      "x1": 0.026537997587454766,
      "y1": 0.927734375,
      "x2": 0.9758745476477684,
      "y2": 0.927734375,
      "angle_deg": 0.0,
      "length": 0.5973416038188885,
      "class": "horizontal"
    },
    {
      "x1": 0.03618817852834741,
      "y1": 0.4306640625,
      "x2": 0.9674306393244874,
      "y2": 0.4306640625,
      "angle_deg": 0.0,
      "length": 0.5859564398325056,
      "class": "horizontal"
    },
    {
      "x1": 0.06393244873341375,
      "y1": 0.5126953125,
      "x2": 0.9336550060313631,
      "y2": 0.5126953125,
      "angle_deg": 0.0,
      "length": 0.5472468822788038,
      "class": "horizontal"
    },
    {
      "x1": 0.033775633293124246,
      "y1": 0.814453125,
      "x2": 0.646562123039807,
      "y2": 0.318359375,
      "angle_deg": -45.0,
      "length": 0.5452890057498184,
      "class": "diagonal"
    },
    {
      "x1": 0.20989143546441497,
      "y1": 0.5224609375,
      "x2": 0.9734620024125452,
      "y2": 0.5224609375,
      "angle_deg": 0.0,
      "length": 0.4804539202253576,
      "class": "horizontal"
    },
    {
      "x1": 0.033775633293124246,
      "y1": 0.7978515625,
      "x2": 0.5476477683956574,
      "y2": 0.3818359375,
      "angle_deg": -45.0,
      "length": 0.45726991427051705,
      "class": "diagonal"
    },
    {
      "x1": 0.40651387213510254,
      "y1": 0.484375,
      "x2": 0.9674306393244874,
      "y2": 0.826171875,
      "angle_deg": 36.968343905516264,
      "length": 0.44174501474242234,
      "class": "diagonal"
    },
    {
      "x1": 0.10615199034981906,
      "y1": 0.7666015625,
      "x2": 0.6682750301568154,
      "y2": 0.482421875,
      "angle_deg": -31.983274091097474,
      "length": 0.4169982853027687,
      "class": "diagonal"
    },
    {
      "x1": 0.10856453558504221,
      "y1": 0.0986328125,
      "x2": 0.7503015681544029,
      "y2": 0.0986328125,
      "angle_deg": 0.0,
      "length": 0.4037938160503795,
      "class": "horizontal"
    },
    {
      "x1": 0.045838359469240045,
      "y1": 0.3876953125,
      "x2": 0.6839565741857659,
      "y2": 0.4052734375,
      "angle_deg": 1.9488209547701218,
      "length": 0.40174915414332196,
      "class": "horizontal"
    },
    {
      "x1": 0.3413751507840772,
      "y1": 0.544921875,
      "x2": 0.9734620024125452,
      "y2": 0.544921875,
      "angle_deg": 0.0,
      "length": 0.3977217285909753,
      "class": "horizontal"
    }
  ],
  "horizon": {
    "y": 0.5126953125,
    "angle_deg": 0.0,
    "confidence": 1.0,
    "method": "both"
  },
  "vanishing_point": {
    "x": 0.4549007169836871,
    "y": 0.5138597173908285,
    "inliers": 3,
    "confidence": 0.6
  },
  "saliency": {
    "peak": [
      0.45958986731001206,
      0.7255859375
    ],
    "regions": [
      {
        "cx": 0.45192416894381393,
        "cy": 0.7329178292410714,
        "x": 0.35102533172496986,
        "y": 0.6123046875,
        "w": 0.22074788902291917,
        "h": 0.271484375,
        "area_frac": 0.034633217732207476
      },
      {
        "cx": 0.6270060079092679,
        "cy": 0.19407511806783032,
        "x": 0.5379975874547648,
        "y": 0.13671875,
        "w": 0.18455971049457176,
        "h": 0.1181640625,
        "area_frac": 0.013329076824487335
      },
      {
        "cx": 0.38167884765486415,
        "cy": 0.3674977777912152,
        "x": 0.3486127864897467,
        "y": 0.3359375,
        "w": 0.06634499396863691,
        "h": 0.0625,
        "area_frac": 0.003043953558504222
      }
    ]
  },
  "faces": [],
  "symmetry": {
    "vertical": 0.9557562182138661,
    "vertical_axis_x": 0.5,
    "horizontal": 0.7297651701010831,
    "horizontal_axis_y": 0.5625
  },
  "subject_anchor": {
    "x": 0.45958986731001206,
    "y": 0.7255859375,
    "source": "saliency"
  },
  "grids": {
    "thirds": 0.17650848206172373,
    "phi": 0.28334620571812047,
    "best": "phi"
  },
  "suggested_primitives": [
    {
      "type": "horizon_line",
      "y": 0.513,
      "angle": 0.0,
      "label": "horizon",
      "confidence": 1.0,
      "why": "luminance split / dominant horizontal (both)"
    },
    {
      "type": "leading_line",
      "points": [
        [
          0.034,
          0.814
        ],
        [
          0.647,
          0.318
        ]
      ],
      "arrow": true,
      "label": "leading line",
      "confidence": 1.0,
      "why": "strong diagonal converging on VP"
    },
    {
      "type": "symmetry_axis",
      "orientation": "vertical",
      "pos": 0.5,
      "confidence": 0.96,
      "why": "strong left/right mirror correlation"
    },
    {
      "type": "leading_line",
      "points": [
        [
          0.034,
          0.798
        ],
        [
          0.548,
          0.382
        ]
      ],
      "arrow": true,
      "label": "leading line",
      "confidence": 0.91,
      "why": "strong diagonal converging on VP"
    }
  ]
}